{
  "__html": "<h1 id=\"task-instance\">Task Instance</h1>\n<h2 id=\"batch-task-instance\">Batch Task Instance</h2>\n<h3 id=\"create-task-instance\">Create Task Instance</h3>\n<p>Click <code>Project Management -&gt; Workflow -&gt; Task Instance</code> to enter the task instance page, as shown in the figure below, click the name of the workflow instance to jump to the DAG diagram of the workflow instance to view the task status.</p>\n<p><img src=\"/img/new_ui/dev/project/batch-task-instance.png\" alt=\"task-instance\"></p>\n<h3 id=\"view-log\">View Log</h3>\n<p>Click the <code>View Log</code> button in the operation column to view the log of the task execution</p>\n<p><img src=\"/img/new_ui/dev/project/task-log.png\" alt=\"task-log\"></p>\n<h2 id=\"stream-task-instance\">Stream Task Instance</h2>\n<p>-Switch to the stream task instance page, as shown in the following figure:</p>\n<p><img src=\"/img/new_ui/dev/project/stream-task-instance.png\" alt=\"task-instance\"></p>\n<ul>\n<li>SavePoint: Click the <code>SavePoint</code> button in the operation column to do stream task savepoint.</li>\n<li>Stop: Click the <code>Stop</code> button in the operation column to stop the stream task.</li>\n</ul>\n",
  "location": [
    "Introduction to Functions",
    "Project",
    "Task Instance"
  ],
  "time": "2025-8-24",
  "structure": [
    {
      "title": "Batch Task Instance",
      "children": [
        {
          "title": "Create Task Instance",
          "children": [],
          "anchor": "create-task-instance"
        },
        {
          "title": "View Log",
          "children": [],
          "anchor": "view-log"
        }
      ],
      "anchor": "batch-task-instance"
    },
    {
      "title": "Stream Task Instance",
      "children": [
        {
          "title": "Create Task Instance",
          "children": [],
          "anchor": "create-task-instance"
        },
        {
          "title": "View Log",
          "children": [],
          "anchor": "view-log"
        }
      ],
      "anchor": "stream-task-instance"
    }
  ],
  "title": "Task Instance",
  "link": "/guide/project/task-instance"
}