{
  "__html": "<h1 id=\"doris\">DORIS</h1>\n<p><img src=\"/img/new_ui/dev/datasource/doris.png\" alt=\"doris\"></p>\n<h2 id=\"datasource-parameters\">Datasource Parameters</h2>\n<table>\n<thead>\n<tr>\n<th><strong>Datasource</strong></th>\n<th><strong>Description</strong></th>\n</tr>\n</thead>\n<tbody>\n<tr>\n<td>Datasource</td>\n<td>Select DORIS.</td>\n</tr>\n<tr>\n<td>Datasource name</td>\n<td>Enter the name of the DataSource.</td>\n</tr>\n<tr>\n<td>Description</td>\n<td>Enter a description of the DataSource.</td>\n</tr>\n<tr>\n<td>IP/Host Name</td>\n<td>Enter the DORIS service IP.(If there are multiple IPs, please separate them with <code>,</code>)</td>\n</tr>\n<tr>\n<td>Port</td>\n<td>Enter the DORIS service port.</td>\n</tr>\n<tr>\n<td>Username</td>\n<td>Set the username for DORIS connection.</td>\n</tr>\n<tr>\n<td>Password</td>\n<td>Set the password for DORIS connection.</td>\n</tr>\n<tr>\n<td>Database name</td>\n<td>Enter the database name of the DORIS connection.</td>\n</tr>\n<tr>\n<td>Jdbc connection parameters</td>\n<td>Parameter settings for DORIS connection, in JSON format.</td>\n</tr>\n</tbody>\n</table>\n<h2 id=\"native-supported\">Native Supported</h2>\n<p>No, read section example in <a href=\"../howto//en-us/docs/3.2.0/guide/installation/datasource-setting\">datasource-setting</a> <code>DataSource Center</code> section to activate\nthis datasource.</p>\n",
  "location": [
    "Introduction to Functions",
    "Data Source",
    "doris"
  ],
  "time": "2023-10-17",
  "structure": [
    {
      "title": "Datasource Parameters",
      "children": [],
      "anchor": "datasource-parameters"
    },
    {
      "title": "Native Supported",
      "children": [],
      "anchor": "native-supported"
    }
  ],
  "title": "DORIS",
  "link": "/guide/datasource/doris"
}