[
  {
    "title": "关于Apache DolphinScheduler",
    "children": [
      {
        "title": "简介",
        "children": [],
        "location": [
          "关于Apache DolphinScheduler",
          "简介"
        ],
        "key": "/About_DolphinScheduler/About_DolphinScheduler"
      },
      {
        "title": "建议配置",
        "children": [],
        "location": [
          "关于Apache DolphinScheduler",
          "建议配置"
        ],
        "key": "/guide/installation/hardware"
      },
      {
        "title": "名称解释",
        "children": [],
        "location": [
          "关于Apache DolphinScheduler",
          "名称解释"
        ],
        "key": "/architecture/designplus"
      }
    ],
    "location": [
      "关于Apache DolphinScheduler"
    ],
    "key": "/关于apache-dolphinscheduler_menu"
  },
  {
    "title": "快速上手",
    "children": [
      {
        "title": "快速上手",
        "children": [],
        "location": [
          "快速上手",
          "快速上手"
        ],
        "key": "/guide/quick-start"
      },
      {
        "title": "用户手册",
        "children": [],
        "location": [
          "快速上手",
          "用户手册"
        ],
        "key": "/guide/system-manual"
      },
      {
        "title": "Docker部署(Docker)",
        "children": [],
        "location": [
          "快速上手",
          "Docker部署(Docker)"
        ],
        "key": "/guide/installation/docker"
      }
    ],
    "location": [
      "快速上手"
    ],
    "key": "/快速上手_menu"
  },
  {
    "title": "部署指南",
    "children": [
      {
        "title": "单机部署(Standalone)",
        "children": [],
        "location": [
          "部署指南",
          "单机部署(Standalone)"
        ],
        "key": "/guide/installation/standalone"
      },
      {
        "title": "伪集群部署(Pseudo-Cluster)",
        "children": [],
        "location": [
          "部署指南",
          "伪集群部署(Pseudo-Cluster)"
        ],
        "key": "/guide/installation/pseudo-cluster"
      },
      {
        "title": "集群部署(Cluster)",
        "children": [],
        "location": [
          "部署指南",
          "集群部署(Cluster)"
        ],
        "key": "/guide/installation/cluster"
      },
      {
        "title": "Kubernetes部署(Kubernetes)",
        "children": [],
        "location": [
          "部署指南",
          "Kubernetes部署(Kubernetes)"
        ],
        "key": "/guide/installation/kubernetes"
      }
    ],
    "location": [
      "部署指南"
    ],
    "key": "/部署指南_menu"
  },
  {
    "title": "功能介绍",
    "children": [
      {
        "title": "指标总览",
        "children": [],
        "location": [
          "功能介绍",
          "指标总览"
        ],
        "key": "/guide/homepage"
      },
      {
        "title": "项目管理",
        "children": [
          {
            "title": "项目列表",
            "children": [],
            "location": [
              "功能介绍",
              "项目管理",
              "项目列表"
            ],
            "key": "/guide/project/project-list"
          },
          {
            "title": "工作流定义",
            "children": [],
            "location": [
              "功能介绍",
              "项目管理",
              "工作流定义"
            ],
            "key": "/guide/project/workflow-definition"
          },
          {
            "title": "工作流实例",
            "children": [],
            "location": [
              "功能介绍",
              "项目管理",
              "工作流实例"
            ],
            "key": "/guide/project/workflow-instance"
          },
          {
            "title": "任务实例",
            "children": [],
            "location": [
              "功能介绍",
              "项目管理",
              "任务实例"
            ],
            "key": "/guide/project/task-instance"
          }
        ],
        "location": [
          "功能介绍",
          "项目管理"
        ],
        "key": "/功能介绍_menu/项目管理_menu"
      },
      {
        "title": "任务类型",
        "children": [
          {
            "title": "Shell",
            "children": [],
            "location": [
              "功能介绍",
              "任务类型",
              "Shell"
            ],
            "key": "/guide/task/shell"
          },
          {
            "title": "SubProcess",
            "children": [],
            "location": [
              "功能介绍",
              "任务类型",
              "SubProcess"
            ],
            "key": "/guide/task/sub-process"
          },
          {
            "title": "Dependent",
            "children": [],
            "location": [
              "功能介绍",
              "任务类型",
              "Dependent"
            ],
            "key": "/guide/task/dependent"
          },
          {
            "title": "Stored Procedure",
            "children": [],
            "location": [
              "功能介绍",
              "任务类型",
              "Stored Procedure"
            ],
            "key": "/guide/task/stored-procedure"
          },
          {
            "title": "SQL",
            "children": [],
            "location": [
              "功能介绍",
              "任务类型",
              "SQL"
            ],
            "key": "/guide/task/sql"
          },
          {
            "title": "Spark",
            "children": [],
            "location": [
              "功能介绍",
              "任务类型",
              "Spark"
            ],
            "key": "/guide/task/spark"
          },
          {
            "title": "MapReduce",
            "children": [],
            "location": [
              "功能介绍",
              "任务类型",
              "MapReduce"
            ],
            "key": "/guide/task/map-reduce"
          },
          {
            "title": "Python",
            "children": [],
            "location": [
              "功能介绍",
              "任务类型",
              "Python"
            ],
            "key": "/guide/task/python"
          },
          {
            "title": "Flink",
            "children": [],
            "location": [
              "功能介绍",
              "任务类型",
              "Flink"
            ],
            "key": "/guide/task/flink"
          },
          {
            "title": "HTTP",
            "children": [],
            "location": [
              "功能介绍",
              "任务类型",
              "HTTP"
            ],
            "key": "/guide/task/http"
          },
          {
            "title": "DataX",
            "children": [],
            "location": [
              "功能介绍",
              "任务类型",
              "DataX"
            ],
            "key": "/guide/task/datax"
          },
          {
            "title": "Pigeon",
            "children": [],
            "location": [
              "功能介绍",
              "任务类型",
              "Pigeon"
            ],
            "key": "/guide/task/pigeon"
          },
          {
            "title": "Conditions",
            "children": [],
            "location": [
              "功能介绍",
              "任务类型",
              "Conditions"
            ],
            "key": "/guide/task/conditions"
          },
          {
            "title": "Switch",
            "children": [],
            "location": [
              "功能介绍",
              "任务类型",
              "Switch"
            ],
            "key": "/guide/task/switch"
          }
        ],
        "location": [
          "功能介绍",
          "任务类型"
        ],
        "key": "/功能介绍_menu/任务类型_menu"
      },
      {
        "title": "参数",
        "children": [
          {
            "title": "内置参数",
            "children": [],
            "location": [
              "功能介绍",
              "参数",
              "内置参数"
            ],
            "key": "/guide/parameter/built-in"
          },
          {
            "title": "全局参数",
            "children": [],
            "location": [
              "功能介绍",
              "参数",
              "全局参数"
            ],
            "key": "/guide/parameter/global"
          },
          {
            "title": "本地参数",
            "children": [],
            "location": [
              "功能介绍",
              "参数",
              "本地参数"
            ],
            "key": "/guide/parameter/local"
          },
          {
            "title": "参数传递",
            "children": [],
            "location": [
              "功能介绍",
              "参数",
              "参数传递"
            ],
            "key": "/guide/parameter/context"
          },
          {
            "title": "参数优先级",
            "children": [],
            "location": [
              "功能介绍",
              "参数",
              "参数优先级"
            ],
            "key": "/guide/parameter/priority"
          }
        ],
        "location": [
          "功能介绍",
          "参数"
        ],
        "key": "/功能介绍_menu/参数_menu"
      },
      {
        "title": "数据源中心",
        "children": [
          {
            "title": "简介",
            "children": [],
            "location": [
              "功能介绍",
              "数据源中心",
              "简介"
            ],
            "key": "/guide/datasource/introduction"
          },
          {
            "title": "MySQL",
            "children": [],
            "location": [
              "功能介绍",
              "数据源中心",
              "MySQL"
            ],
            "key": "/guide/datasource/mysql"
          },
          {
            "title": "PostgreSQL",
            "children": [],
            "location": [
              "功能介绍",
              "数据源中心",
              "PostgreSQL"
            ],
            "key": "/guide/datasource/postgresql"
          },
          {
            "title": "HIVE",
            "children": [],
            "location": [
              "功能介绍",
              "数据源中心",
              "HIVE"
            ],
            "key": "/guide/datasource/hive"
          },
          {
            "title": "Spark",
            "children": [],
            "location": [
              "功能介绍",
              "数据源中心",
              "Spark"
            ],
            "key": "/guide/datasource/spark"
          }
        ],
        "location": [
          "功能介绍",
          "数据源中心"
        ],
        "key": "/功能介绍_menu/数据源中心_menu"
      },
      {
        "title": "告警",
        "children": [
          {
            "title": "告警组件向导 ",
            "children": [],
            "location": [
              "功能介绍",
              "告警",
              "告警组件向导 "
            ],
            "key": "/guide/alert/alert_plugin_user_guide"
          },
          {
            "title": "企业微信",
            "children": [],
            "location": [
              "功能介绍",
              "告警",
              "企业微信"
            ],
            "key": "/guide/alert/enterprise-wechat"
          }
        ],
        "location": [
          "功能介绍",
          "告警"
        ],
        "key": "/功能介绍_menu/告警_menu"
      },
      {
        "title": "资源中心",
        "children": [],
        "location": [
          "功能介绍",
          "资源中心"
        ],
        "key": "/guide/resource"
      },
      {
        "title": "监控中心",
        "children": [],
        "location": [
          "功能介绍",
          "监控中心"
        ],
        "key": "/guide/monitor"
      },
      {
        "title": "安全中心",
        "children": [],
        "location": [
          "功能介绍",
          "安全中心"
        ],
        "key": "/guide/security"
      },
      {
        "title": "API调用",
        "children": [],
        "location": [
          "功能介绍",
          "API调用"
        ],
        "key": "/guide/open-api"
      },
      {
        "title": "Flink调用",
        "children": [],
        "location": [
          "功能介绍",
          "Flink调用"
        ],
        "key": "/guide/flink-call"
      },
      {
        "title": "升级",
        "children": [],
        "location": [
          "功能介绍",
          "升级"
        ],
        "key": "/guide/upgrade"
      },
      {
        "title": "扩/缩容",
        "children": [],
        "location": [
          "功能介绍",
          "扩/缩容"
        ],
        "key": "/guide/expansion-reduction"
      }
    ],
    "location": [
      "功能介绍"
    ],
    "key": "/功能介绍_menu"
  },
  {
    "title": "高级指南",
    "children": [
      {
        "title": "架构设计",
        "children": [],
        "location": [
          "高级指南",
          "架构设计"
        ],
        "key": "/architecture/design"
      },
      {
        "title": "元数据文档",
        "children": [],
        "location": [
          "高级指南",
          "元数据文档"
        ],
        "key": "/architecture/metadata"
      },
      {
        "title": "配置文件",
        "children": [],
        "location": [
          "高级指南",
          "配置文件"
        ],
        "key": "/architecture/configuration"
      },
      {
        "title": "任务结构",
        "children": [],
        "location": [
          "高级指南",
          "任务结构"
        ],
        "key": "/architecture/task-structure"
      },
      {
        "title": "负载均衡",
        "children": [],
        "location": [
          "高级指南",
          "负载均衡"
        ],
        "key": "/architecture/load-balance"
      }
    ],
    "location": [
      "高级指南"
    ],
    "key": "/高级指南_menu"
  },
  {
    "title": "可观测性",
    "children": [
      {
        "title": "SkyWalking-Agent",
        "children": [],
        "location": [
          "可观测性",
          "SkyWalking-Agent"
        ],
        "key": "/guide/observability/skywalking-agent"
      }
    ],
    "location": [
      "可观测性"
    ],
    "key": "/可观测性_menu"
  }
]